math_ops_viviani/__init__.py
math_ops_viviani/math_viviani.py
math_ops_viviani-0.0.1.dist-info/METADATA
math_ops_viviani-0.0.1.dist-info/WHEEL
math_ops_viviani-0.0.1.dist-info/top_level.txt
math_ops_viviani-0.0.1.dist-info/RECORD
