Metadata-Version: 2.1
Name: math-ops-viviani
Version: 0.0.1
Summary: The package math_operations
Home-page: https://github.com/vivianikelly/math-operations-package
Author: Viviani Pedroso
Author-email: viani22@gmail.com
Requires-Python: >=3.8
